ambition_metadata_rules/__init__.py
ambition_metadata_rules/apps.py
ambition_metadata_rules/predicates.py
ambition_metadata_rules/urls.py
ambition_metadata_rules/metadata_rules/__init__.py
ambition_metadata_rules/metadata_rules/csf_stop_requisition_rule_group.py
ambition_metadata_rules/metadata_rules/education_rule_group.py
ambition_metadata_rules/metadata_rules/medical_expenses_rule_group.py
ambition_metadata_rules/metadata_rules/qpcr_requisition_rule_group.py
ambition_metadata_rules/metadata_rules/requisition_rule_groups.py
ambition_metadata_rules/tests/__init__.py
ambition_metadata_rules/tests/models.py
ambition_metadata_rules/tests/test_predicates.py
ambition_metadata_rules-0.1.24.dist-info/AUTHORS
ambition_metadata_rules-0.1.24.dist-info/LICENSE
ambition_metadata_rules-0.1.24.dist-info/METADATA
ambition_metadata_rules-0.1.24.dist-info/WHEEL
ambition_metadata_rules-0.1.24.dist-info/top_level.txt
ambition_metadata_rules-0.1.24.dist-info/RECORD
