Metadata-Version: 2.1
Name: ambition-metadata-rules
Version: 0.1.24
Summary: Metadata rules for ambition/edc project
Home-page: https://github.com/ambition-trial/ambition-metadata-rules
Author: Erik van Widenfelt
Author-email: ew2789@gmail.com
License: GPL license, see LICENSE
Keywords: django edc clinicedc ambition
Platform: UNKNOWN
Classifier: Environment :: Web Environment
Classifier: Framework :: Django
Classifier: Intended Audience :: Developers
Classifier: Intended Audience :: Science/Research
Classifier: License :: OSI Approved :: GNU General Public License v3 (GPLv3)
Classifier: Operating System :: OS Independent
Classifier: Programming Language :: Python :: 3.6
Classifier: Programming Language :: Python :: 3.7
Classifier: Topic :: Internet :: WWW/HTTP
Classifier: Topic :: Internet :: WWW/HTTP :: Dynamic Content
Requires-Python: >=3.7
Requires-Dist: ambition-ae
Requires-Dist: ambition-labs
Requires-Dist: ambition-lists
Requires-Dist: ambition-prn
Requires-Dist: ambition-rando
Requires-Dist: ambition-sites
Requires-Dist: ambition-screening
Requires-Dist: ambition-subject
Requires-Dist: ambition-reference
Requires-Dist: ambition-form-validators
Requires-Dist: ambition-visit-schedule
Requires-Dist: edc-action-item
Requires-Dist: edc-metadata
Requires-Dist: edc-metadata-rules
Requires-Dist: edc-offstudy
Requires-Dist: edc-constants
Requires-Dist: edc-reportable
